odoo/addons/stock_buffer_route/README.rst
odoo/addons/stock_buffer_route/__init__.py
odoo/addons/stock_buffer_route/__manifest__.py
odoo/addons/stock_buffer_route/i18n/es_AR.po
odoo/addons/stock_buffer_route/i18n/it.po
odoo/addons/stock_buffer_route/i18n/pt_BR.po
odoo/addons/stock_buffer_route/i18n/stock_buffer_route.pot
odoo/addons/stock_buffer_route/models/__init__.py
odoo/addons/stock_buffer_route/models/stock_buffer.py
odoo/addons/stock_buffer_route/readme/CONTRIBUTORS.rst
odoo/addons/stock_buffer_route/readme/DESCRIPTION.rst
odoo/addons/stock_buffer_route/readme/USAGE.rst
odoo/addons/stock_buffer_route/static/description/icon.png
odoo/addons/stock_buffer_route/static/description/index.html
odoo/addons/stock_buffer_route/tests/__init__.py
odoo/addons/stock_buffer_route/tests/test_stock_buffer_route.py
odoo/addons/stock_buffer_route/views/stock_buffer_views.xml
odoo/addons/stock_buffer_route/wizards/__init__.py
odoo/addons/stock_buffer_route/wizards/make_procurement_buffer.py
odoo/addons/stock_buffer_route/wizards/make_procurement_buffer_view.xml
odoo14_addon_stock_buffer_route-14.0.1.3.0.dist-info/METADATA
odoo14_addon_stock_buffer_route-14.0.1.3.0.dist-info/WHEEL
odoo14_addon_stock_buffer_route-14.0.1.3.0.dist-info/top_level.txt
odoo14_addon_stock_buffer_route-14.0.1.3.0.dist-info/RECORD
